sample/__init__.py
sample/bootstrap.yaml
sample/datamodel.py
sample/handlers.py
sample/service.py
sample/configs/__init__.py
sample/configs/addressbook-local.yaml
sample/configs/application.yaml
sample/configs/nacos.py
sample/data/__init__.py
sample/database/__init__.py
sample/database/addressbook_db.py
sample/database/db_engines.py
sample/schema/__init__.py
sample/schema/address-book-v1.0.json
sample/tests/__init__.py
sample/tests/integration/__init__.py
sample/tests/integration/addrservice_test.py
sample/tests/integration/tornado_app_addreservice_handlers_test.py
sample/tests/unit/__init__.py
sample/tests/unit/address_data_test.py
sample/tests/unit/addressbook_db_test.py
sample/tests/unit/datamodel_test.py
sample/tests/unit/tornado_app_handlers_test.py
tormicro/__init__.py
tormicro/app.py
tormicro/config.py
tormicro/doc.py
tormicro/server.py
tormicro/rest/__init__.py
tormicro/rest/mediatypes.py
tormicro/rest/types.py
tormicro/utils/__init__.py
tormicro/utils/logutils.py
tormicro/utils/modutils.py
tormicro-0.0.1.17.dist-info/LICENSE
tormicro-0.0.1.17.dist-info/METADATA
tormicro-0.0.1.17.dist-info/WHEEL
tormicro-0.0.1.17.dist-info/entry_points.txt
tormicro-0.0.1.17.dist-info/top_level.txt
tormicro-0.0.1.17.dist-info/RECORD
