Metadata-Version: 2.1
Name: tormicro
Version: 0.0.1.17
Summary: A tornado-based microservice booster
Home-page: https://github.com/bailaohe/parade
Author: He Bai
Author-email: bailaohe@gmail.com
License: UNKNOWN
Keywords: tornado,microservice,web,restful
Platform: any
Classifier: Development Status :: 4 - Beta
Classifier: Intended Audience :: Developers
Classifier: License :: OSI Approved :: Apache Software License
Classifier: Programming Language :: Python :: 3
Classifier: Topic :: Database
Classifier: Topic :: Software Development :: Libraries :: Python Modules
Classifier: Operating System :: Unix
Classifier: Operating System :: MacOS :: MacOS X
Classifier: Operating System :: Microsoft :: Windows
Classifier: Operating System :: POSIX
Requires-Dist: aiofiles (==0.4.0)
Requires-Dist: aiohttp (==3.6.2)
Requires-Dist: aiotask-context (==0.6.1)
Requires-Dist: argparse (==1.4.0)
Requires-Dist: asyncio (==3.4.3)
Requires-Dist: asynctest (==0.13.0)
Requires-Dist: coverage (==5.0.3)
Requires-Dist: flake8 (==3.7.9)
Requires-Dist: jsonschema (==3.2.0)
Requires-Dist: logfmt (==0.4)
Requires-Dist: mypy (==0.761)
Requires-Dist: PyYAML (==5.4)
Requires-Dist: requests (==2.22.0)
Requires-Dist: tornado (==6.0.3)
Requires-Dist: mergedeep (==1.3.4)
Requires-Dist: aliyun-log-python-sdk (==0.6.56)
Requires-Dist: tornado-swagger (==1.2.10)
Requires-Dist: pyconvert (==0.6.3)
